{
    "payload":  {
                    "steps":  [
                                  {
                                      "op":  "RUN_SCRIPT",
                                      "path":  "agents/agent_01/run_agent.py"
                                  },
                                  {
                                      "op":  "RUN_SCRIPT",
                                      "path":  "agents/agent_02/run_agent.py"
                                  },
                                  {
                                      "op":  "RUN_SCRIPT",
                                      "path":  "agents/agent_03/run_agent.py"
                                  },
                                  {
                                      "op":  "RUN_SCRIPT",
                                      "path":  "agents/agent_04/run_agent.py"
                                  },
                                  {
                                      "op":  "RUN_SCRIPT",
                                      "path":  "agents/agent_05/run_agent.py"
                                  },
                                  {
                                      "op":  "RUN_SCRIPT",
                                      "path":  "agents/agent_06/run_agent.py"
                                  },
                                  {
                                      "op":  "RUN_SCRIPT",
                                      "path":  "agents/agent_07/run_agent.py"
                                  },
                                  {
                                      "op":  "RUN_SCRIPT",
                                      "path":  "agents/agent_08/run_agent.py"
                                  },
                                  {
                                      "op":  "RUN_SCRIPT",
                                      "path":  "agents/agent_09/run_agent.py"
                                  },
                                  {
                                      "op":  "RUN_SCRIPT",
                                      "path":  "agents/agent_1/run_agent.py"
                                  },
                                  {
                                      "op":  "RUN_SCRIPT",
                                      "path":  "agents/agent_10/run_agent.py"
                                  },
                                  {
                                      "op":  "RUN_SCRIPT",
                                      "path":  "agents/agent_11/run_agent.py"
                                  },
                                  {
                                      "op":  "RUN_SCRIPT",
                                      "path":  "agents/agent_12/run_agent.py"
                                  },
                                  {
                                      "op":  "RUN_SCRIPT",
                                      "path":  "agents/agent_13/run_agent.py"
                                  },
                                  {
                                      "op":  "RUN_SCRIPT",
                                      "path":  "agents/agent_14/run_agent.py"
                                  },
                                  {
                                      "op":  "RUN_SCRIPT",
                                      "path":  "agents/agent_15/run_agent.py"
                                  },
                                  {
                                      "op":  "RUN_SCRIPT",
                                      "path":  "agents/agent_16/run_agent.py"
                                  },
                                  {
                                      "op":  "RUN_SCRIPT",
                                      "path":  "agents/agent_17/run_agent.py"
                                  },
                                  {
                                      "op":  "RUN_SCRIPT",
                                      "path":  "agents/agent_18/run_agent.py"
                                  },
                                  {
                                      "op":  "RUN_SCRIPT",
                                      "path":  "agents/agent_19/run_agent.py"
                                  },
                                  {
                                      "op":  "RUN_SCRIPT",
                                      "path":  "agents/agent_2/run_agent.py"
                                  },
                                  {
                                      "op":  "RUN_SCRIPT",
                                      "path":  "agents/agent_20/run_agent.py"
                                  },
                                  {
                                      "op":  "RUN_SCRIPT",
                                      "path":  "agents/agent_21/run_agent.py"
                                  },
                                  {
                                      "op":  "RUN_SCRIPT",
                                      "path":  "agents/agent_22/run_agent.py"
                                  },
                                  {
                                      "op":  "RUN_SCRIPT",
                                      "path":  "agents/agent_23/run_agent.py"
                                  },
                                  {
                                      "op":  "RUN_SCRIPT",
                                      "path":  "agents/agent_24/run_agent.py"
                                  },
                                  {
                                      "op":  "RUN_SCRIPT",
                                      "path":  "agents/agent_25/run_agent.py"
                                  },
                                  {
                                      "op":  "RUN_SCRIPT",
                                      "path":  "agents/agent_26/run_agent.py"
                                  },
                                  {
                                      "op":  "RUN_SCRIPT",
                                      "path":  "agents/agent_27/run_agent.py"
                                  },
                                  {
                                      "op":  "RUN_SCRIPT",
                                      "path":  "agents/agent_28/run_agent.py"
                                  },
                                  {
                                      "op":  "RUN_SCRIPT",
                                      "path":  "agents/agent_29/run_agent.py"
                                  },
                                  {
                                      "op":  "RUN_SCRIPT",
                                      "path":  "agents/agent_3/run_agent.py"
                                  },
                                  {
                                      "op":  "RUN_SCRIPT",
                                      "path":  "agents/agent_30/run_agent.py"
                                  },
                                  {
                                      "op":  "RUN_SCRIPT",
                                      "path":  "agents/agent_31/run_agent.py"
                                  },
                                  {
                                      "op":  "RUN_SCRIPT",
                                      "path":  "agents/agent_32/run_agent.py"
                                  },
                                  {
                                      "op":  "RUN_SCRIPT",
                                      "path":  "agents/agent_33/run_agent.py"
                                  },
                                  {
                                      "op":  "RUN_SCRIPT",
                                      "path":  "agents/agent_34/run_agent.py"
                                  },
                                  {
                                      "op":  "RUN_SCRIPT",
                                      "path":  "agents/agent_35/run_agent.py"
                                  },
                                  {
                                      "op":  "RUN_SCRIPT",
                                      "path":  "agents/agent_36/run_agent.py"
                                  },
                                  {
                                      "op":  "RUN_SCRIPT",
                                      "path":  "agents/agent_37/run_agent.py"
                                  },
                                  {
                                      "op":  "RUN_SCRIPT",
                                      "path":  "agents/agent_38/run_agent.py"
                                  },
                                  {
                                      "op":  "RUN_SCRIPT",
                                      "path":  "agents/agent_39/run_agent.py"
                                  },
                                  {
                                      "op":  "RUN_SCRIPT",
                                      "path":  "agents/agent_4/run_agent.py"
                                  },
                                  {
                                      "op":  "RUN_SCRIPT",
                                      "path":  "agents/agent_40/run_agent.py"
                                  },
                                  {
                                      "op":  "RUN_SCRIPT",
                                      "path":  "agents/agent_41/run_agent.py"
                                  },
                                  {
                                      "op":  "RUN_SCRIPT",
                                      "path":  "agents/agent_42/run_agent.py"
                                  },
                                  {
                                      "op":  "RUN_SCRIPT",
                                      "path":  "agents/agent_43/run_agent.py"
                                  },
                                  {
                                      "op":  "RUN_SCRIPT",
                                      "path":  "agents/agent_44/run_agent.py"
                                  },
                                  {
                                      "op":  "RUN_SCRIPT",
                                      "path":  "agents/agent_45/run_agent.py"
                                  },
                                  {
                                      "op":  "RUN_SCRIPT",
                                      "path":  "agents/agent_46/run_agent.py"
                                  },
                                  {
                                      "op":  "RUN_SCRIPT",
                                      "path":  "agents/agent_47/run_agent.py"
                                  },
                                  {
                                      "op":  "RUN_SCRIPT",
                                      "path":  "agents/agent_48/run_agent.py"
                                  },
                                  {
                                      "op":  "RUN_SCRIPT",
                                      "path":  "agents/agent_49/run_agent.py"
                                  },
                                  {
                                      "op":  "RUN_SCRIPT",
                                      "path":  "agents/agent_5/run_agent.py"
                                  },
                                  {
                                      "op":  "RUN_SCRIPT",
                                      "path":  "agents/agent_50/run_agent.py"
                                  },
                                  {
                                      "op":  "RUN_SCRIPT",
                                      "path":  "agents/agent_6/run_agent.py"
                                  },
                                  {
                                      "op":  "RUN_SCRIPT",
                                      "path":  "agents/agent_7/run_agent.py"
                                  },
                                  {
                                      "op":  "RUN_SCRIPT",
                                      "path":  "agents/agent_8/run_agent.py"
                                  },
                                  {
                                      "op":  "RUN_SCRIPT",
                                      "path":  "agents/agent_9/run_agent.py"
                                  }
                              ]
                }
}
